{
 "cells": [
  {
   "cell_type": "code",
   "execution_count": 9,
   "metadata": {},
   "outputs": [],
   "source": [
    "#factorial\n",
    "\n",
    "def ab(n):\n",
    "    if n==0:\n",
    "        return 1\n",
    "    else:\n",
    "        return n*ab(n-1)"
   ]
  },
  {
   "cell_type": "code",
   "execution_count": 10,
   "metadata": {},
   "outputs": [
    {
     "data": {
      "text/plain": [
       "120"
      ]
     },
     "execution_count": 10,
     "metadata": {},
     "output_type": "execute_result"
    }
   ],
   "source": [
    "ab(5)"
   ]
  },
  {
   "cell_type": "code",
   "execution_count": 11,
   "metadata": {},
   "outputs": [],
   "source": [
    "import dis"
   ]
  },
  {
   "cell_type": "code",
   "execution_count": 12,
   "metadata": {},
   "outputs": [
    {
     "name": "stdout",
     "output_type": "stream",
     "text": [
      "  4           0 LOAD_FAST                0 (n)\n",
      "              2 LOAD_CONST               1 (0)\n",
      "              4 COMPARE_OP               2 (==)\n",
      "              6 POP_JUMP_IF_FALSE       12\n",
      "\n",
      "  5           8 LOAD_CONST               2 (1)\n",
      "             10 RETURN_VALUE\n",
      "\n",
      "  7     >>   12 LOAD_FAST                0 (n)\n",
      "             14 LOAD_GLOBAL              0 (ab)\n",
      "             16 LOAD_FAST                0 (n)\n",
      "             18 LOAD_CONST               2 (1)\n",
      "             20 BINARY_SUBTRACT\n",
      "             22 CALL_FUNCTION            1\n",
      "             24 BINARY_MULTIPLY\n",
      "             26 RETURN_VALUE\n",
      "             28 LOAD_CONST               0 (None)\n",
      "             30 RETURN_VALUE\n"
     ]
    }
   ],
   "source": [
    "dis.dis(ab)"
   ]
  },
  {
   "cell_type": "code",
   "execution_count": null,
   "metadata": {},
   "outputs": [],
   "source": []
  }
 ],
 "metadata": {
  "kernelspec": {
   "display_name": "Python 3",
   "language": "python",
   "name": "python3"
  },
  "language_info": {
   "codemirror_mode": {
    "name": "ipython",
    "version": 3
   },
   "file_extension": ".py",
   "mimetype": "text/x-python",
   "name": "python",
   "nbconvert_exporter": "python",
   "pygments_lexer": "ipython3",
   "version": "3.8.5"
  }
 },
 "nbformat": 4,
 "nbformat_minor": 4
}
